clanki/__init__.py
clanki/__main__.py
clanki/audio.py
clanki/auth.py
clanki/cli.py
clanki/collection.py
clanki/config.py
clanki/config_store.py
clanki/sync.py
clanki/render/__init__.py
clanki/render/html.py
clanki/review/__init__.py
clanki/review/session.py
clanki/tui/__init__.py
clanki/tui/app.py
clanki/tui/render.py
clanki/tui/screens/__init__.py
clanki/tui/screens/collection_lock.py
clanki/tui/screens/deck_picker.py
clanki/tui/screens/done.py
clanki/tui/screens/review.py
clanki/tui/widgets/__init__.py
clanki/tui/widgets/ascii_logo.py
clanki/tui/widgets/card_view.py
clanki/tui/widgets/logo_data.py
clanki/tui/widgets/stats_bar.py
clanki-0.1.2.dist-info/METADATA
clanki-0.1.2.dist-info/WHEEL
clanki-0.1.2.dist-info/entry_points.txt
clanki-0.1.2.dist-info/licenses/LICENSE
clanki-0.1.2.dist-info/RECORD
