Metadata-Version: 2.4
Name: clanki
Version: 0.1.2
Summary: Terminal-based Anki review client using native Anki backend
Project-URL: Homepage, https://github.com/alvenw/clanki
Project-URL: Repository, https://github.com/alvenw/clanki
Project-URL: Issues, https://github.com/alvenw/clanki/issues
Author: Alven Wang
License-Expression: AGPL-3.0-or-later
License-File: LICENSE
Keywords: anki,flashcards,spaced-repetition,terminal,tui
Classifier: Development Status :: 3 - Alpha
Classifier: Environment :: Console
Classifier: Intended Audience :: Education
Classifier: Intended Audience :: End Users/Desktop
Classifier: License :: OSI Approved :: GNU Affero General Public License v3
Classifier: Operating System :: OS Independent
Classifier: Programming Language :: Python :: 3
Classifier: Programming Language :: Python :: 3.10
Classifier: Programming Language :: Python :: 3.11
Classifier: Programming Language :: Python :: 3.12
Classifier: Topic :: Education
Requires-Python: >=3.10
Requires-Dist: anki==25.9.2
Requires-Dist: textual-image[textual]>=0.7
Requires-Dist: textual>=0.50
Provides-Extra: dev
Requires-Dist: mypy; extra == 'dev'
Requires-Dist: pytest; extra == 'dev'
Requires-Dist: ruff; extra == 'dev'
